statick_tool/plugins/discovery/pddl.py
statick_tool/plugins/tool/val_parser.py
statick_tool/plugins/tool/val_validate.py
statick_tool/rsc/planning-config.yaml
statick_tool/rsc/planning-profile.yaml
statick_planning-0.3.0.dist-info/LICENSE
statick_planning-0.3.0.dist-info/METADATA
statick_planning-0.3.0.dist-info/WHEEL
statick_planning-0.3.0.dist-info/entry_points.txt
statick_planning-0.3.0.dist-info/top_level.txt
statick_planning-0.3.0.dist-info/RECORD
