Metadata-Version: 2.2
Name: statick-planning
Version: 0.3.0
Summary: Statick analysis plugins for planning files.
Author: NIWC Pacific
License: CC0-1.0
Project-URL: Homepage, https://github.com/tdenewiler/statick-planning
Project-URL: Bug Tracker, https://github.com/tdenewiler/statick-planning/issues
Classifier: License :: CC0 1.0 Universal (CC0 1.0) Public Domain Dedication
Classifier: Programming Language :: Python :: 3
Classifier: Programming Language :: Python :: 3.9
Classifier: Programming Language :: Python :: 3.10
Classifier: Programming Language :: Python :: 3.11
Classifier: Programming Language :: Python :: 3.12
Classifier: Programming Language :: Python :: 3.13
Classifier: Topic :: Software Development :: Testing
Requires-Python: >=3.9
License-File: LICENSE
Requires-Dist: importlib_metadata
Requires-Dist: statick
Requires-Dist: types-docutils
Provides-Extra: test
Requires-Dist: coverage; extra == "test"
Requires-Dist: mock; extra == "test"
Requires-Dist: pytest; extra == "test"
Requires-Dist: pytest-cov; extra == "test"
Requires-Dist: tox; extra == "test"
Requires-Dist: tox-gh-actions; extra == "test"
Provides-Extra: docs
Requires-Dist: sphinx==1.7.9; extra == "docs"
Requires-Dist: yaml-1.3; extra == "docs"
